setup.cfg
setup.py
libsaas_gitlab/__init__.py
libsaas_gitlab/branches.py
libsaas_gitlab/commits.py
libsaas_gitlab/groups.py
libsaas_gitlab/issues.py
libsaas_gitlab/keys.py
libsaas_gitlab/merge_requests.py
libsaas_gitlab/projects.py
libsaas_gitlab/resource.py
libsaas_gitlab/service.py
libsaas_gitlab/users.py
libsaas_gitlab.egg-info/PKG-INFO
libsaas_gitlab.egg-info/SOURCES.txt
libsaas_gitlab.egg-info/dependency_links.txt
libsaas_gitlab.egg-info/requires.txt
libsaas_gitlab.egg-info/top_level.txt
test/__init__.py
test/run_tests.py
test/test_gitlab.py