Metadata-Version: 1.1
Name: libsaas-gitlab
Version: 0.3.0.dev0
Summary: Python wrapper for GitLab API v3
Home-page: https://gitlab.com/bor-sh-infrastructure/libsaas_gitlab
Author: b-sh
Author-email: b-sh@gmx.net
License: MIT
Download-URL: https://gitlab.com/bor-sh-infrastructure/libsaas_gitlab/repository/archive.tar.gz?ref=v0.3
Platform: any
Classifier: Development Status :: 3 - Alpha
Classifier: Environment :: Console
Classifier: Intended Audience :: Developers
Classifier: Intended Audience :: End Users/Desktop
Classifier: License :: OSI Approved :: MIT License
Classifier: Operating System :: OS Independent
Classifier: Programming Language :: Python
Classifier: Topic :: Database
Classifier: Topic :: Software Development :: Libraries :: Python Modules
